inappropriate_notifications/__init__.py
inappropriate_notifications/command_line.py
inappropriate_notifications/notifications.json
inappropriate_notifications/notify.py
inappropriate_notifications/version.py
inappropriate_notifications/icons/cal.ico
inappropriate_notifications/icons/facebook.ico
inappropriate_notifications/icons/facebook.png
inappropriate_notifications/icons/grindr.ico
inappropriate_notifications/icons/grindr.png
inappropriate_notifications/icons/imessage.ico
inappropriate_notifications/icons/imessage.png
inappropriate_notifications/icons/mail.ico
inappropriate_notifications/icons/mail.png
inappropriate_notifications/icons/slack.ico
inappropriate_notifications/icons/slack.png
inappropriate_notifications/images/female/Afşar.ico
inappropriate_notifications/images/female/Afşar.jpg
inappropriate_notifications/images/female/Agathe.ico
inappropriate_notifications/images/female/Agathe.jpg
inappropriate_notifications/images/female/Alessa.ico
inappropriate_notifications/images/female/Alessa.jpg
inappropriate_notifications/images/female/Alet.ico
inappropriate_notifications/images/female/Alet.jpg
inappropriate_notifications/images/female/Alice.ico
inappropriate_notifications/images/female/Alice.jpg
inappropriate_notifications/images/female/Alisa.ico
inappropriate_notifications/images/female/Alisa.jpg
inappropriate_notifications/images/female/Alizee.ico
inappropriate_notifications/images/female/Alizee.jpg
inappropriate_notifications/images/female/Ana.ico
inappropriate_notifications/images/female/Ana.jpg
inappropriate_notifications/images/female/Anni.ico
inappropriate_notifications/images/female/Anni.jpg
inappropriate_notifications/images/female/Ashley.ico
inappropriate_notifications/images/female/Ashley.jpg
inappropriate_notifications/images/female/Astrid.ico
inappropriate_notifications/images/female/Astrid.jpg
inappropriate_notifications/images/female/Aurore.ico
inappropriate_notifications/images/female/Aurore.jpg
inappropriate_notifications-0.3.7.dist-info/METADATA
inappropriate_notifications-0.3.7.dist-info/RECORD
inappropriate_notifications-0.3.7.dist-info/WHEEL
inappropriate_notifications-0.3.7.dist-info/entry_points.txt
inappropriate_notifications-0.3.7.dist-info/top_level.txt
