Metadata-Version: 2.1
Name: inappropriate-notifications
Version: 0.3.7
Summary: Display inappropriate notifications at random intervals
Home-page: https://github.com/riley-martine/inappropriate-notifications
Author: Riley Martine
Author-email: riley.martine.0@gmail.com
License: MIT
Keywords: notifications notify inappropriate present
Platform: UNKNOWN
Classifier: Development Status :: 3 - Alpha
Classifier: Environment :: Win32 (MS Windows)
Classifier: Environment :: X11 Applications
Classifier: License :: OSI Approved :: MIT License
Classifier: Intended Audience :: Developers
Classifier: Intended Audience :: End Users/Desktop
Classifier: Natural Language :: English
Classifier: Operating System :: Microsoft :: Windows :: Windows 10
Classifier: Operating System :: POSIX :: Linux
Classifier: Programming Language :: Python :: 3.6
Classifier: Topic :: Artistic Software
Requires-Python: ~=3.6
